thugshaker/__init__.py
thugshaker/player.py
thugshaker/assets/audio.mp3
thugshaker/assets/video.mp4
thugshaker-1.0.2.dist-info/LICENSE
thugshaker-1.0.2.dist-info/METADATA
thugshaker-1.0.2.dist-info/WHEEL
thugshaker-1.0.2.dist-info/entry_points.txt
thugshaker-1.0.2.dist-info/top_level.txt
thugshaker-1.0.2.dist-info/RECORD
