Metadata-Version: 2.1
Name: thugshaker
Version: 1.0.2
Summary: you've got an ass on you alright
Home-page: https://pypi.org/project/thugshaker/
Author: Niggeshwar Faggotlal
License: MIT
Classifier: Programming Language :: Python :: 3
Classifier: License :: OSI Approved :: MIT License
Classifier: Operating System :: OS Independent
License-File: LICENSE
Requires-Dist: pygame
Requires-Dist: opencv-python
Requires-Dist: keyboard
